sigiq/__init__.py
sigiq/functions.py
sigiq/decorators/__init__.py
sigiq/decorators/li_token_tracking/__init__.py
sigiq/decorators/li_token_tracking/token_tracking.py
sigiq-0.3.1.dist-info/METADATA
sigiq-0.3.1.dist-info/WHEEL
sigiq-0.3.1.dist-info/top_level.txt
sigiq-0.3.1.dist-info/RECORD
