Metadata-Version: 2.1
Name: sigiq
Version: 0.3.1
Requires-Dist: requests
Requires-Dist: openai
Requires-Dist: llama-index-core ==0.10.15
